tox_pyenv.py
tox_pyenv-1.1.0.dist-info/DESCRIPTION.rst
tox_pyenv-1.1.0.dist-info/METADATA
tox_pyenv-1.1.0.dist-info/RECORD
tox_pyenv-1.1.0.dist-info/WHEEL
tox_pyenv-1.1.0.dist-info/entry_points.txt
tox_pyenv-1.1.0.dist-info/metadata.json
tox_pyenv-1.1.0.dist-info/top_level.txt
