Metadata-Version: 1.1
Name: tox-pyenv
Version: 1.1.0
Summary: tox plugin that makes tox use `pyenv which` to find python executables
Home-page: https://github.com/samstav/tox-pyenv
Author: Sam Stavinoha
Author-email: smlstvnh@gmail.com
License: Apache License, Version 2.0
Keywords: tox pyenv python ae48885f
Platform: UNKNOWN
Classifier: Intended Audience :: Developers
Classifier: License :: OSI Approved :: Apache Software License
Classifier: Operating System :: OS Independent
Classifier: Topic :: Software Development
Classifier: Programming Language :: Python
Classifier: Programming Language :: Python :: 2
Classifier: Programming Language :: Python :: 2.6
Classifier: Programming Language :: Python :: 2.7
Classifier: Programming Language :: Python :: 3
Classifier: Programming Language :: Python :: 3.3
Classifier: Programming Language :: Python :: 3.4
Classifier: Programming Language :: Python :: 3.5
Classifier: Programming Language :: Python :: Implementation :: CPython
Classifier: Programming Language :: Python :: Implementation :: PyPy
